{
    "status": 0,
    "message": "成功",
    "productList": [
        {
            "productId": "11779140",
            "price": 120,
            "hostAvatarUrl": "https://img.meituan.net/avatar/42f5d4710ee9d5093847a290c0b9a7b4302779.jpg",
            "title": "威海文登区中心整套配品质厨房烤箱蓝牙音箱",
            "rentType": 0,
            "layoutRoom": 1,
            "maxGuestNumber": 4,
            "locationArea": "文登实验中学",
            "starRating": 50,
            "commentNumber": 2,
            "coverImage": "https://img.meituan.net/iphoenixhd/fa60e2e7babf2067dcfb6b0ffbc2f69559381.jpg",
            "favCount": 44,
            "poiId": "736276226",
            "dpPoiId": "736276226"
        },
        {
            "productId": "9247683",
            "price": 158,
            "hostAvatarUrl": "https://img.meituan.net/avatar/8451aac157b034166d19419d565bc18315707.jpg",
            "title": "【朴宿】&地暖 巨幕投影 韩乐坊观海复式 摩洛哥风情浪漫纱幔   近汽车站  高铁站  刘公岛 海上公园旁",
            "rentType": 0,
            "layoutRoom": 2,
            "maxGuestNumber": 4,
            "locationArea": "九隆大厦",
            "starRating": 48,
            "commentNumber": 32,
            "coverImage": "https://img.meituan.net/phoenix/80ac2fd18d0cbf5dddcf5baa3a6a5b8a1645665.jpg",
            "favCount": 723,
            "poiId": "1631348112",
            "dpPoiId": "1631348112"
        },
        {
            "productId": "7975482",
            "price": 109,
            "hostAvatarUrl": "https://img.meituan.net/avatar/3264e481f7f243a5694b41a519515bcd303980.jpg",
            "title": "【有暖气】紧邻国际海水浴场山东大学威海分校西门独享整套房源",
            "rentType": 0,
            "layoutRoom": 1,
            "maxGuestNumber": 2,
            "locationArea": "山东大学",
            "starRating": 50,
            "commentNumber": 16,
            "coverImage": "https://img.meituan.net/phoenix/e1f39c4bfb37c6ed6741f2d102efc2971048748.jpg",
            "favCount": 210,
            "poiId": "765639631",
            "dpPoiId": "765639631"
        },
        {
            "productId": "7176719",
            "price": 70,
            "hostAvatarUrl": "https://img.meituan.net/avatar/d0ec57eb5ece337273a066f81ac154d614606.jpg",
            "title": "韩乐坊零度青年民宿舒适大床房",
            "rentType": 1,
            "layoutRoom": 12,
            "maxGuestNumber": 2,
            "locationArea": "韩国风情街",
            "starRating": 50,
            "commentNumber": 3,
            "coverImage": "https://img.meituan.net/iphoenix/1cd5763bbf4b0f84e402d57303732796604181.jpg",
            "favCount": 70,
            "poiId": "194330191",
            "dpPoiId": "131360345"
        },
        {
            "productId": "11023529",
            "price": 118,
            "hostAvatarUrl": "https://img.meituan.net/avatar/444ab2882b1e30a2e123200a6c6a1aa118605.jpg",
            "title": "已消毒99富城公寓",
            "rentType": 0,
            "layoutRoom": 1,
            "maxGuestNumber": 3,
            "locationArea": "富城101站前广场",
            "starRating": 48,
            "commentNumber": 22,
            "coverImage": "https://img.meituan.net/phoenix/697913426df1d88d3bcf8ad137071a68137810.jpg",
            "favCount": 184,
            "poiId": "728663033",
            "dpPoiId": "728663033"
        },
        {
            "productId": "7406884",
            "price": 170,
            "hostAvatarUrl": "https://img.meituan.net/avatar/e1824674df4fb8a4fba8cba2c043b48216960.jpg",
            "title": "荣成自在澜湾民宿/ 九龙城购物广场/高层躺在床上看大海/楼下小公园儿童游乐场  /樱花湖看大天鹅/可以做饭 /拎包入住",
            "rentType": 0,
            "layoutRoom": 1,
            "maxGuestNumber": 2,
            "locationArea": null,
            "starRating": 47,
            "commentNumber": 6,
            "coverImage": "https://img.meituan.net/phoenix/ee75ecc258310d12fba065c1509297ee5695267.jpg",
            "favCount": 69,
            "poiId": "195041844",
            "dpPoiId": "132058480"
        }
    ]
}